{
	"id": "https://raw.githubusercontent.com/apiadapter/schema-org-gen/master/generated_schemas/MedicalSign.json",
	"title": "Medical Sign",
	"format": "http://schema.org/MedicalSign",
	"media": {"type": "application/json;profile=http://schema.org/MedicalSign"},
	"allOf": [{"$ref": "https://raw.githubusercontent.com/apiadapter/schema-org-gen/master/generated_schemas/MedicalSignOrSymptom.json"}],
	"type": "object",
	"properties": {
		"identifyingExam": {"$ref": "https://raw.githubusercontent.com/apiadapter/schema-org-gen/master/generated_schemas/PhysicalExam.json#/definitions/possibleRefArray"},
		"identifyingTest": {"$ref": "https://raw.githubusercontent.com/apiadapter/schema-org-gen/master/generated_schemas/MedicalTest.json#/definitions/possibleRefArray"}
	},
	"definitions": {
		"array": {
			"type": "array",
			"items": {"$ref": "#"}
		},
		"possibleRef": {
			"oneOf": [
				{"$ref": "#"},
				{
					"type": "string",
					"format": "uri",
					"links": [{
						"rel": "full",
						"href": "{+$}"
					}]
				}
			]
		},
		"possibleRefArray": {
			"oneOf": [
				{
					"type": "string",
					"format": "uri",
					"links": [{
						"rel": "full",
						"href": "{+$}"
					}]
				},
				{
					"type": "array",
					"items": {"$ref": "#/definitions/possibleRef"}
				}
			]
		}
	}
}