{
	"id": "https://raw.githubusercontent.com/apiadapter/schema-org-gen/master/generated_schemas/VideoGallery.json",
	"title": "Video Gallery",
	"format": "http://schema.org/VideoGallery",
	"media": {"type": "application/json;profile=http://schema.org/VideoGallery"},
	"allOf": [{"$ref": "https://raw.githubusercontent.com/apiadapter/schema-org-gen/master/generated_schemas/CollectionPage.json"}],
	"definitions": {
		"array": {
			"type": "array",
			"items": {"$ref": "#"}
		},
		"possibleRef": {
			"oneOf": [
				{"$ref": "#"},
				{
					"type": "string",
					"format": "uri",
					"links": [{
						"rel": "full",
						"href": "{+$}"
					}]
				}
			]
		},
		"possibleRefArray": {
			"oneOf": [
				{
					"type": "string",
					"format": "uri",
					"links": [{
						"rel": "full",
						"href": "{+$}"
					}]
				},
				{
					"type": "array",
					"items": {"$ref": "#/definitions/possibleRef"}
				}
			]
		}
	}
}